Metadata-Version: 1.1
Name: byt
Version: 1.0.12
Summary: Version-independent bytes-chains
Home-page: https://github.com/ceyzeriat/byt/
Author: Guillaume Schworer
Author-email: guillaume.schworer@gmail.com
License: GNU
Download-URL: https://github.com/ceyzeriat/byt/tree/master/dist
Keywords: bytes,chain,octet,string,hexa,hexadecimal,python2,python3,version,independent
Platform: UNKNOWN
Classifier: Development Status :: 4 - Beta
Classifier: Environment :: Console
Classifier: Intended Audience :: Developers
Classifier: License :: OSI Approved :: GNU General Public License v3 or later (GPLv3+)
Classifier: Operating System :: OS Independent
Classifier: Programming Language :: Python
